LICENSE
MANIFEST.in
README.rst
setup.py
account_manager/__init__.py
account_manager/middleware.py
account_manager/urls.py
account_manager/views.py
django_account_manager.egg-info/PKG-INFO
django_account_manager.egg-info/SOURCES.txt
django_account_manager.egg-info/dependency_links.txt
django_account_manager.egg-info/top_level.txt