Metadata-Version: 1.0
Name: django-account-manager
Version: 0.0.3
Summary: Experimental implementation of Account Management and Session Identification of Mozilla Labs
Home-page: http://forge.2metz.fr/p/django-account-manager/
Author: Francois de Metz
Author-email: francois@2metz.fr
License: BSD
Platform: UNKNOWN
Classifier: Development Status :: 4 - Beta
Classifier: Environment :: Web Environment
Classifier: Framework :: Django
Classifier: Intended Audience :: Developers
Classifier: License :: OSI Approved :: BSD License
Classifier: Operating System :: OS Independent
Classifier: Programming Language :: Python
Classifier: Topic :: Software Development :: Libraries :: Python Modules
